orcakit_api/__init__.py
orcakit_api/asgi_transport.py
orcakit_api/asyncio.py
orcakit_api/cli.py
orcakit_api/command.py
orcakit_api/config.py
orcakit_api/cron_scheduler.py
orcakit_api/errors.py
orcakit_api/executor_entrypoint.py
orcakit_api/feature_flags.py
orcakit_api/graph.py
orcakit_api/http.py
orcakit_api/http_metrics.py
orcakit_api/http_metrics_utils.py
orcakit_api/logging.py
orcakit_api/metadata.py
orcakit_api/patch.py
orcakit_api/queue_entrypoint.py
orcakit_api/route.py
orcakit_api/schema.py
orcakit_api/self_hosted_logs.py
orcakit_api/self_hosted_metrics.py
orcakit_api/serde.py
orcakit_api/server.py
orcakit_api/sse.py
orcakit_api/state.py
orcakit_api/store.py
orcakit_api/stream.py
orcakit_api/thread_ttl.py
orcakit_api/traceblock.py
orcakit_api/validation.py
orcakit_api/webhook.py
orcakit_api/worker.py
orcakit_api/api/__init__.py
orcakit_api/api/a2a.py
orcakit_api/api/assistants.py
orcakit_api/api/mcp.py
orcakit_api/api/meta.py
orcakit_api/api/openapi.py
orcakit_api/api/runs.py
orcakit_api/api/store.py
orcakit_api/api/threads.py
orcakit_api/api/ui.py
orcakit_api/auth/__init__.py
orcakit_api/auth/custom.py
orcakit_api/auth/middleware.py
orcakit_api/auth/noop.py
orcakit_api/auth/studio_user.py
orcakit_api/auth/langsmith/__init__.py
orcakit_api/auth/langsmith/backend.py
orcakit_api/auth/langsmith/client.py
orcakit_api/channels/__init__.py
orcakit_api/channels/a2a.py
orcakit_api/channels/base.py
orcakit_api/channels/mcp.py
orcakit_api/channels/openai.py
orcakit_api/channels/wework.py
orcakit_api/grpc/__init__.py
orcakit_api/grpc/client.py
orcakit_api/grpc/config_conversion.py
orcakit_api/grpc/generated/__init__.py
orcakit_api/grpc/generated/core_api_pb2.py
orcakit_api/grpc/generated/core_api_pb2.pyi
orcakit_api/grpc/generated/core_api_pb2_grpc.py
orcakit_api/grpc/generated/engine_common_pb2.py
orcakit_api/grpc/generated/engine_common_pb2.pyi
orcakit_api/grpc/generated/engine_common_pb2_grpc.py
orcakit_api/grpc/generated/enum_durability_pb2.py
orcakit_runner-0.6.3.dist-info/METADATA
orcakit_runner-0.6.3.dist-info/WHEEL
orcakit_runner-0.6.3.dist-info/entry_points.txt
orcakit_runner-0.6.3.dist-info/licenses/LICENSE
orcakit_runner-0.6.3.dist-info/RECORD
